srsly-2.4.8.dist-info/METADATA
srsly-2.4.8.dist-info/LICENSE
srsly-2.4.8.dist-info/entry_points.txt
srsly-2.4.8.dist-info/WHEEL
srsly-2.4.8.dist-info/RECORD
srsly-2.4.8.dist-info/zip-safe
srsly-2.4.8.dist-info/top_level.txt
srsly/_json_api.py
srsly/_msgpack_api.py
srsly/_pickle_api.py
srsly/about.py
srsly/_yaml_api.py
srsly/util.py
srsly/__init__.py
srsly/ruamel_yaml/cyaml.py
srsly/ruamel_yaml/error.py
srsly/ruamel_yaml/emitter.py
srsly/ruamel_yaml/tokens.py
srsly/ruamel_yaml/parser.py
srsly/ruamel_yaml/anchor.py
srsly/ruamel_yaml/events.py
srsly/ruamel_yaml/compat.py
srsly/ruamel_yaml/configobjwalker.py
srsly/ruamel_yaml/composer.py
srsly/ruamel_yaml/comments.py
srsly/ruamel_yaml/reader.py
srsly/ruamel_yaml/representer.py
srsly/ruamel_yaml/nodes.py
srsly/ruamel_yaml/scalarstring.py
srsly/ruamel_yaml/util.py
srsly/ruamel_yaml/serializer.py
srsly/ruamel_yaml/resolver.py
srsly/ruamel_yaml/dumper.py
srsly/ruamel_yaml/scanner.py
srsly/ruamel_yaml/loader.py
srsly/ruamel_yaml/__init__.py
srsly/ruamel_yaml/timestamp.py
srsly/ruamel_yaml/scalarint.py
srsly/ruamel_yaml/scalarfloat.py
srsly/ruamel_yaml/constructor.py
srsly/ruamel_yaml/scalarbool.py
srsly/ruamel_yaml/main.py
srsly/msgpack/unpack_define.h
srsly/msgpack/unpack_template.h
srsly/msgpack/pack.h
srsly/msgpack/exceptions.py
srsly/msgpack/buff_converter.h
srsly/msgpack/_ext_type.py
srsly/msgpack/_packer.cpython-39-x86_64-linux-gnu.so
srsly/msgpack/sysdep.h
srsly/msgpack/_unpacker.cpython-39-x86_64-linux-gnu.so
srsly/msgpack/_msgpack_numpy.py
srsly/msgpack/_packer.cpp
srsly/msgpack/_unpacker.cpp
srsly/msgpack/_unpacker.pyx
srsly/msgpack/util.py
srsly/msgpack/pack_template.h
srsly/msgpack/__init__.py
srsly/msgpack/_packer.pyx
srsly/msgpack/_version.py
srsly/msgpack/unpack.h
srsly/ujson/JSONtoObj.c
srsly/ujson/version.h
srsly/ujson/py_defines.h
srsly/ujson/ujson.c
srsly/ujson/__init__.py
srsly/ujson/objToJSON.c
srsly/ujson/ujson.cpython-39-x86_64-linux-gnu.so
srsly/ujson/lib/ultrajson.h
srsly/ujson/lib/dconv_wrapper.cc
srsly/ujson/lib/ultrajsondec.c
srsly/ujson/lib/ultrajsonenc.c
srsly/tests/test_msgpack_api.py
srsly/tests/test_pickle_api.py
srsly/tests/test_yaml_api.py
